in_silico_cancer_cell-0.2.3.dist-info/METADATA
in_silico_cancer_cell-0.2.3.dist-info/WHEEL
in_silico_cancer_cell/plot.py
in_silico_cancer_cell/py.typed
in_silico_cancer_cell/utils.py
in_silico_cancer_cell/_in_rusty_silico.pyi
in_silico_cancer_cell/__init__.py
in_silico_cancer_cell/_in_rusty_silico.cp310-win32.pyd
in_silico_cancer_cell-0.2.3.dist-info/RECORD
