Metadata-Version: 2.3
Name: in_silico_cancer_cell
Version: 0.2.3
Classifier: Programming Language :: Rust
Classifier: Programming Language :: Python :: Implementation :: CPython
Classifier: Programming Language :: Python :: Implementation :: PyPy
Summary: Simulation of an electrophysiological A549 cancer cell model using individual ion channels across the membrane
Requires-Python: >=3.10
Project-URL: homepage, https://in-silico-cancer-cell.waldert.at/
Project-URL: repository, https://github.com/MrP01/InSilicoCancerCell
